rag_bench/__init__.py
rag_bench/baseline.py
rag_bench/constants.py
rag_bench/data.py
rag_bench/evaluator.py
rag_bench/helper.py
rag_bench/results.py
rag_bench-0.2.17.dist-info/METADATA
rag_bench-0.2.17.dist-info/WHEEL
rag_bench-0.2.17.dist-info/top_level.txt
rag_bench-0.2.17.dist-info/RECORD
