Metadata-Version: 2.4
Name: rag-bench
Version: 0.2.17
Summary: RAG benchmarking tool
Home-page: https://github.com/
Author: Sergei Averkiev
Author-email: averoo@gmail.com
Project-URL: Bug Tracker, https://github.com/
Classifier: Programming Language :: Python :: 3
Classifier: License :: OSI Approved :: GNU General Public License v3 (GPLv3)
Classifier: Operating System :: OS Independent
Requires-Python: >=3.8
